trellis/__init__.py
trellis/datasets/__init__.py
trellis/datasets/components.py
trellis/datasets/sparse_feat2render.py
trellis/datasets/sparse_structure.py
trellis/datasets/sparse_structure_latent.py
trellis/datasets/structured_latent.py
trellis/datasets/structured_latent2render.py
trellis/models/__init__.py
trellis/models/sparse_elastic_mixin.py
trellis/models/sparse_structure_flow.py
trellis/models/sparse_structure_vae.py
trellis/models/structured_latent_flow.py
trellis/models/structured_latent_vae/__init__.py
trellis/models/structured_latent_vae/base.py
trellis/models/structured_latent_vae/decoder_gs.py
trellis/models/structured_latent_vae/decoder_mesh.py
trellis/models/structured_latent_vae/decoder_rf.py
trellis/models/structured_latent_vae/encoder.py
trellis/modules/norm.py
trellis/modules/spatial.py
trellis/modules/utils.py
trellis/modules/attention/__init__.py
trellis/modules/attention/full_attn.py
trellis/modules/attention/modules.py
trellis/modules/sparse/__init__.py
trellis/modules/sparse/basic.py
trellis/modules/sparse/linear.py
trellis/modules/sparse/nonlinearity.py
trellis/modules/sparse/norm.py
trellis/modules/sparse/spatial.py
trellis/modules/sparse/attention/__init__.py
trellis/modules/sparse/attention/full_attn.py
trellis/modules/sparse/attention/modules.py
trellis/modules/sparse/attention/serialized_attn.py
trellis/modules/sparse/attention/windowed_attn.py
trellis/modules/sparse/conv/__init__.py
trellis/modules/sparse/conv/conv_spconv.py
trellis/modules/sparse/conv/conv_torchsparse.py
trellis/modules/sparse/transformer/__init__.py
trellis/modules/sparse/transformer/blocks.py
trellis/modules/sparse/transformer/modulated.py
trellis/modules/transformer/__init__.py
trellis/modules/transformer/blocks.py
trellis/modules/transformer/modulated.py
trellis/pipelines/__init__.py
trellis/pipelines/base.py
trellis/pipelines/trellis_image_to_3d.py
trellis/pipelines/trellis_text_to_3d.py
trellis/pipelines/samplers/__init__.py
trellis/pipelines/samplers/base.py
trellis_3d_ms-0.1.0.dist-info/licenses/LICENSE
trellis_3d_ms-0.1.0.dist-info/METADATA
trellis_3d_ms-0.1.0.dist-info/WHEEL
trellis_3d_ms-0.1.0.dist-info/top_level.txt
trellis_3d_ms-0.1.0.dist-info/RECORD
