Metadata-Version: 2.4
Name: trellis-3d-ms
Version: 0.1.0
Summary: A fork of Microsoft's TRELLIS for scalable 3D generation from images and text.
Author: Microsoft TRELLIS Team
Author-email: Hajare Vinay <vinayhajare2004@gmail.com>
License:     MIT License
Project-URL: Homepage, https://trellis3d.github.io/
Project-URL: Source, https://github.com/VinayHajare/TRELLIS
Project-URL: Original Repository, https://github.com/microsoft/TRELLIS
Requires-Python: >=3.8
License-File: LICENSE
Requires-Dist: pytorch>=2.4.0
Requires-Dist: torchvision>=0.19.0
Requires-Dist: pillow
Requires-Dist: imageio
Requires-Dist: imageio-ffmpeg
Requires-Dist: tqdm
Requires-Dist: easydict
Requires-Dist: opencv-python-headless
Requires-Dist: scipy
Requires-Dist: ninja
Requires-Dist: rembg
Requires-Dist: onnxruntime
Requires-Dist: trimesh
Requires-Dist: open3d
Requires-Dist: xatlas
Requires-Dist: pyvista
Requires-Dist: pymeshfix
Requires-Dist: igraph
Requires-Dist: transformers
Dynamic: license-file
